midpay/__init__.py
midpay/crawlers.py
midpay/scripts.py
midpay/settings.py
midpay-0.0.1.dist-info/LICENSE
midpay-0.0.1.dist-info/METADATA
midpay-0.0.1.dist-info/WHEEL
midpay-0.0.1.dist-info/entry_points.txt
midpay-0.0.1.dist-info/top_level.txt
midpay-0.0.1.dist-info/RECORD
