Metadata-Version: 2.1
Name: midpay
Version: 0.0.1
Summary: Auto Pay midtrans VA by CLI
Author-email: Agung Yuliyanto <agung.96tm@gmail.com>
Project-URL: Homepage, https://github.com/BetterToPractice/midpay
Project-URL: Bug Tracker, https://github.com/BetterToPractice/midpay/issues
Classifier: Programming Language :: Python :: 3
Requires-Python: >=3.7
License-File: LICENSE
Requires-Dist: click (==8.1.6)
Requires-Dist: Scrapy (==2.9.0)
